{
  "$schema": "https://mintlify.com/docs.json",
  "theme": "mint",
  "name": "Meestream.ai",
  "colors": {
    "primary": "#FD6316",
    "light": "#FF8A4C",
    "dark": "#CC4F12"
  },
  "favicon": "favicon.svg",
  "navigation": {
    "tabs": [
      {
        "tab": "Guides",
        "groups": [
          {
            "group": "Getting Started",
            "pages": [
              "guides/index"
            ]
          },
          {
            "group": "Bot Integration",
            "pages": [
              "guides/zoom-bot-guide",
              "guides/zoom-bot-guide-2"
            ]
          }
        ]
      },
      {
        "tab": "API Reference",
        "groups": [
          {
            "group": "API Documentation",
            "pages": [
              "api-reference/introduction"
            ]
          },
          {
            "group": "Bot Endpoints",
            "pages": [
              "api-reference/endpoint/post-create-bot",
              "api-reference/endpoint/get-bot-status",
              "api-reference/endpoint/get-bot-audio",
              "api-reference/endpoint/get-bot-transcript",
              "api-reference/endpoint/get-remove-bot",
              "api-reference/endpoint/get-bot-speaker-timeline",
              "api-reference/endpoint/get-bot-chat",
              "api-reference/endpoint/get-bot-screenshot"
            ]
          },
          {
            "group": "Transcript Endpoints",
            "pages": [
              "api-reference/endpoint/get-transcript"
            ]
          },
          {
            "group": "Calendar Endpoints",
            "pages": [
              "api-reference/endpoint/post-create-calendar"
            ]
          }
        ]
      }
    ]
  },
  "logo": {
    "light": "/logo/logo.svg",
    "dark": "/logo/logo.svg",
    "text": "Meestream.ai"
  },
  "navbar": {

    "primary": {
      "type": "button",
      "label": "Dashboard",
      "href": "https://app.meetstream.ai/"
    }
  },
  "homePage": "guides/index"
}